python_swos_lite/__init__.py
python_swos_lite/client.py
python_swos_lite/endpoint.py
python_swos_lite/http.py
python_swos_lite/utils.py
python_swos_lite/endpoints/__init__.py
python_swos_lite/endpoints/link.py
python_swos_lite/endpoints/poe.py
python_swos_lite/endpoints/sys.py
python_swos_lite-0.0.5.dist-info/METADATA
python_swos_lite-0.0.5.dist-info/WHEEL
python_swos_lite-0.0.5.dist-info/licenses/LICENSE
python_swos_lite-0.0.5.dist-info/RECORD
