Metadata-Version: 2.4
Name: python-swos-lite
Version: 0.0.5
Summary: Python library to interact with MikroTik SwitchOS Lite
Project-URL: Homepage, https://github.com/probert94/python-swos-lite
Author: Robert Pattis
License-Expression: MIT
License-File: LICENSE
Keywords: api,mikrotik,switchos,switchos lite
Requires-Python: >=3.10
Requires-Dist: demjson3>=3.0.6
Provides-Extra: aiohttp
Requires-Dist: aiohttp>=3.12; extra == 'aiohttp'
Provides-Extra: httpx
Requires-Dist: httpx>=0.28; extra == 'httpx'
